ipfs_tk_generics/__init__.py
ipfs_tk_generics/base_client.py
ipfs_tk_generics/client.py
ipfs_tk_generics/files.py
ipfs_tk_generics/ipns.py
ipfs_tk_generics/peers.py
ipfs_tk_generics/pubsub.py
ipfs_tk_generics/tunnels.py
ipfs_tk_peer_monitor/__init__.py
ipfs_tk_transmission/__init__.py
ipfs_tk_transmission/config.py
ipfs_tk_transmission/conversation_basics.py
ipfs_tk_transmission/conversations.py
ipfs_tk_transmission/errors.py
ipfs_tk_transmission/file_transmission.py
ipfs_tk_transmission/log.py
ipfs_tk_transmission/transmission.py
ipfs_tk_transmission/utils.py
ipfs_tk-0.1.11.dist-info/METADATA
ipfs_tk-0.1.11.dist-info/WHEEL
ipfs_tk-0.1.11.dist-info/top_level.txt
ipfs_tk-0.1.11.dist-info/RECORD
