Metadata-Version: 2.4
Name: ipfs_tk
Version: 0.1.11
Summary: A set of tools for working with IPFS in Python, agnostic of Python-IPFS interfaces.
Author: emendir
Project-URL: Homepage, https://ipfs.io/ipns/k2k4r8k7h909zdodsvbxe32sahpfdkqcqqn1npblummw4df6iv7dj5xh#IPFS-Toolkit
Project-URL: Github, https://github.com/emendir/IPFS-Toolkit-Python
Classifier: Programming Language :: Python :: 3
Classifier: Operating System :: OS Independent
Requires-Python: >=3.6
